metnet/__init__.py
metnet/utils.py
metnet/data/__init__.py
metnet/data/merge_single_band.py
metnet/layers/ConditionTime.py
metnet/layers/ConditionWithTimeMetNet2.py
metnet/layers/ConvGRU.py
metnet/layers/ConvLSTM.py
metnet/layers/CoordConv.py
metnet/layers/DilatedCondConv.py
metnet/layers/DownSampler.py
metnet/layers/LeadTimeConditioner.py
metnet/layers/MBConv.py
metnet/layers/MaxViT.py
metnet/layers/MultiheadSelfAttention2D.py
metnet/layers/PartitionAttention.py
metnet/layers/Preprocessor.py
metnet/layers/RelativePositionBias.py
metnet/layers/SqueezeExcitation.py
metnet/layers/StochasticDepth.py
metnet/layers/TimeDistributed.py
metnet/layers/__init__.py
metnet/layers/utils.py
metnet/models/__init__.py
metnet/models/metnet.py
metnet/models/metnet2.py
metnet/models/metnet_pv.py
metnet/models/metnet_single_shot.py
metnet-4.1.21.dist-info/licenses/LICENSE
metnet-4.1.21.dist-info/METADATA
metnet-4.1.21.dist-info/WHEEL
metnet-4.1.21.dist-info/top_level.txt
metnet-4.1.21.dist-info/RECORD
