Metadata-Version: 2.4
Name: metnet
Version: 4.1.21
Summary: PyTorch MetNet Implementation
Home-page: https://github.com/openclimatefix/metnet
Author: Jacob Bieker
Author-email: jacob@openclimatefix.org
License: MIT License
Keywords: artificial intelligence,deep learning,transformer,attention mechanism,metnet,forecasting,remote-sensing
Classifier: Development Status :: 4 - Beta
Classifier: Intended Audience :: Developers
Classifier: Topic :: Scientific/Engineering :: Artificial Intelligence
Classifier: License :: OSI Approved :: MIT License
Classifier: Programming Language :: Python :: 3.6
License-File: LICENSE
Requires-Dist: einops>=0.3.0
Requires-Dist: numpy>=1.19.5
Requires-Dist: torchvision>=0.10.0
Requires-Dist: antialiased_cnns
Requires-Dist: axial_attention
Requires-Dist: pytorch_msssim
Requires-Dist: huggingface_hub
Provides-Extra: train
Requires-Dist: ocf_datapipes; extra == "train"
Requires-Dist: pytorch-lightning; extra == "train"
Dynamic: author
Dynamic: author-email
Dynamic: classifier
Dynamic: description
Dynamic: description-content-type
Dynamic: home-page
Dynamic: keywords
Dynamic: license
Dynamic: license-file
Dynamic: provides-extra
Dynamic: requires-dist
Dynamic: summary
